CHANGELOG.md
LICENSE
MANIFEST.in
README.md
setup.py
ois/__init__.py
ois/sdk/__init__.py
ois/sdk/build.py
ois/sdk/config.py
ois/sdk/constant.py
ois/sdk/error.py
ois/sdk/request.py
ois/sdk/unpack.py
ois/sdk/client/__init__.py
ois/sdk/client/upload_client.py
ois/sdk/service/__init__.py
ois/sdk/service/bucket.py
ois/sdk/service/ois.py
ois/sdk/service/qingstor.py
ois/sdk/utils/__init__.py
ois/sdk/utils/file_chunk.py
ois/sdk/utils/helper.py
ois_sdk.egg-info/PKG-INFO
ois_sdk.egg-info/SOURCES.txt
ois_sdk.egg-info/dependency_links.txt
ois_sdk.egg-info/namespace_packages.txt
ois_sdk.egg-info/requires.txt
ois_sdk.egg-info/top_level.txt