Metadata-Version: 2.1
Name: ois-sdk
Version: 1.0.0
Summary: The official OIS SDK for the Python programming language.
Home-page: https://github.com/shanhe-nsccjn/ois-sdk-python
Author: shanhe SDK Group
Author-email: sdk_group@shanhe.com
License: Apache License 2.0
Platform: UNKNOWN
Classifier: Development Status :: 5 - Production/Stable
Classifier: Intended Audience :: Developers
Classifier: Natural Language :: English
Classifier: License :: OSI Approved :: Apache Software License
Classifier: Programming Language :: Python
Classifier: Programming Language :: Python :: 3
Classifier: Programming Language :: Python :: 3.6
Classifier: Programming Language :: Python :: 3.7
Classifier: Programming Language :: Python :: 3.8
Classifier: Programming Language :: Python :: 3.9
